ad_pack/__init__.py
ad_pack/test_package.py
ad_pack-0.3.dist-info/METADATA
ad_pack-0.3.dist-info/WHEEL
ad_pack-0.3.dist-info/top_level.txt
ad_pack-0.3.dist-info/RECORD
