Metadata-Version: 2.1
Name: ad-pack
Version: 0.3
Summary: package testing lib
Home-page: UNKNOWN
Author: UNKNOWN
Author-email: abhishek.adhril@gmail.com
License: UNKNOWN
Platform: UNKNOWN
